ToolGPT/__init__.py
ToolGPT/chat_gpt_with_functions.py
ToolGPT-0.0.1.dist-info/LICENSE
ToolGPT-0.0.1.dist-info/METADATA
ToolGPT-0.0.1.dist-info/WHEEL
ToolGPT-0.0.1.dist-info/top_level.txt
ToolGPT-0.0.1.dist-info/RECORD
